[
  {
    "Timestamp": "2025-05-22 14:57:40",
    "Seller": "Greenball",
    "Stock": 38,
    "Price": 0.144,
    "Price_rub": 11.5,
    "Currency": "USD",
    "Position": 955,
    "DisplayPosition": 1,
    "Online": true
  },
  {
    "Timestamp": "2025-05-22 14:57:40",
    "Seller": "Stempiex",
    "Stock": 210,
    "Price": 0.146,
    "Price_rub": 11.66,
    "Currency": "USD",
    "Position": 956,
    "DisplayPosition": 2,
    "Online": true
  },
  {
    "Timestamp": "2025-05-22 14:57:40",
    "Seller": "Heqpp",
    "Stock": 17,
    "Price": 0.146,
    "Price_rub": 11.66,
    "Currency": "USD",
    "Position": 957,
    "DisplayPosition": 3,
    "Online": true
  },
  {
    "Timestamp": "2025-05-22 14:57:40",
    "Seller": "ksarun",
    "Stock": 70,
    "Price": 0.147,
    "Price_rub": 11.74,
    "Currency": "USD",
    "Position": 958,
    "DisplayPosition": 4,
    "Online": true
  },
  {
    "Timestamp": "2025-05-22 14:57:40",
    "Seller": "Dadae",
    "Stock": 70,
    "Price": 0.147,
    "Price_rub": 11.74,
    "Currency": "USD",
    "Position": 959,
    "DisplayPosition": 5,
    "Online": true
  }
]